Metadata-Version: 2.4
Name: bigecyhmm
Version: 0.1.8
Summary: Predict biogeochemical cycles from protein fasta files.
License: GPL-3.0-or-later
Project-URL: Homepage, https://github.com/ArnaudBelcour/bigecyhmm
Project-URL: Changelog, https://github.com/ArnaudBelcour/bigecyhmm/blob/main/CHANGELOG.md
License-File: LICENSE
Requires-Dist: pyhmmer
Requires-Dist: pillow
Provides-Extra: visualisation
Requires-Dist: pandas; extra == "visualisation"
Requires-Dist: matplotlib; extra == "visualisation"
Requires-Dist: seaborn; extra == "visualisation"
Provides-Extra: custom
Requires-Dist: networkx; extra == "custom"
Requires-Dist: matplotlib; extra == "custom"
Provides-Extra: test
Requires-Dist: pytest; extra == "test"
Dynamic: license-file
